svgio/__init__.py
svgio/svgio.py
svgio-0.0.1.dist-info/METADATA
svgio-0.0.1.dist-info/WHEEL
svgio-0.0.1.dist-info/licenses/LICENCE
svgio-0.0.1.dist-info/RECORD
