Metadata-Version: 2.4
Name: svgio
Version: 0.0.1
Summary: Sphinx extension for drawio embedding
Author: Sergey Aparin
License-Expression: MIT
License-File: LICENCE
Classifier: Operating System :: OS Independent
Classifier: Programming Language :: Python :: 3
Requires-Python: >=3.8
